[
  {
    "id": "1664426",
    "level": 3,
    "level_name": {
      "local": "ບ້ານ",
      "en": "Village"
    },
    "name": {
      "local": "Ban Donhiang",
      "en": "Ban Donhiang",
      "slug": "ban-donhiang-1664426"
    },
    "code": {
      "id": "1664426",
      "iso": null
    },
    "parent": {
      "id": "VI-06",
      "level": 2,
      "name": {
        "local": "Meun",
        "en": "Meun",
        "slug": "meun-vi-06"
      }
    },
    "ancestors": [
      {
        "id": "VI",
        "level": 1,
        "name": {
          "local": "Vientiane",
          "en": "Vientiane Province",
          "slug": "vientiane-province-vi"
        }
      },
      {
        "id": "VI-06",
        "level": 2,
        "name": {
          "local": "Meun",
          "en": "Meun",
          "slug": "meun-vi-06"
        }
      }
    ],
    "children_count": {},
    "zip_codes": [],
    "geo": {
      "lat": "18.077",
      "lon": "101.794"
    },
    "metadata": {},
    "source": {}
  },
  {
    "id": "1941637",
    "level": 3,
    "level_name": {
      "local": "ບ້ານ",
      "en": "Village"
    },
    "name": {
      "local": "Ban Houaytankèo",
      "en": "Ban Houaytankeo",
      "slug": "ban-houaytankeo-1941637"
    },
    "code": {
      "id": "1941637",
      "iso": null
    },
    "parent": {
      "id": "VI-06",
      "level": 2,
      "name": {
        "local": "Meun",
        "en": "Meun",
        "slug": "meun-vi-06"
      }
    },
    "ancestors": [
      {
        "id": "VI",
        "level": 1,
        "name": {
          "local": "Vientiane",
          "en": "Vientiane Province",
          "slug": "vientiane-province-vi"
        }
      },
      {
        "id": "VI-06",
        "level": 2,
        "name": {
          "local": "Meun",
          "en": "Meun",
          "slug": "meun-vi-06"
        }
      }
    ],
    "children_count": {},
    "zip_codes": [],
    "geo": {
      "lat": "18.043",
      "lon": "101.899"
    },
    "metadata": {},
    "source": {}
  },
  {
    "id": "1662197",
    "level": 3,
    "level_name": {
      "local": "ບ້ານ",
      "en": "Village"
    },
    "name": {
      "local": "Ban Moun",
      "en": "Ban Moun",
      "slug": "ban-moun-1662197"
    },
    "code": {
      "id": "1662197",
      "iso": null
    },
    "parent": {
      "id": "VI-06",
      "level": 2,
      "name": {
        "local": "Meun",
        "en": "Meun",
        "slug": "meun-vi-06"
      }
    },
    "ancestors": [
      {
        "id": "VI",
        "level": 1,
        "name": {
          "local": "Vientiane",
          "en": "Vientiane Province",
          "slug": "vientiane-province-vi"
        }
      },
      {
        "id": "VI-06",
        "level": 2,
        "name": {
          "local": "Meun",
          "en": "Meun",
          "slug": "meun-vi-06"
        }
      }
    ],
    "children_count": {},
    "zip_codes": [],
    "geo": {
      "lat": "18.41",
      "lon": "101.958"
    },
    "metadata": {},
    "source": {}
  },
  {
    "id": "1661969",
    "level": 3,
    "level_name": {
      "local": "ບ້ານ",
      "en": "Village"
    },
    "name": {
      "local": "Ban Nahat",
      "en": "Ban Nahat",
      "slug": "ban-nahat-1661969"
    },
    "code": {
      "id": "1661969",
      "iso": null
    },
    "parent": {
      "id": "VI-06",
      "level": 2,
      "name": {
        "local": "Meun",
        "en": "Meun",
        "slug": "meun-vi-06"
      }
    },
    "ancestors": [
      {
        "id": "VI",
        "level": 1,
        "name": {
          "local": "Vientiane",
          "en": "Vientiane Province",
          "slug": "vientiane-province-vi"
        }
      },
      {
        "id": "VI-06",
        "level": 2,
        "name": {
          "local": "Meun",
          "en": "Meun",
          "slug": "meun-vi-06"
        }
      }
    ],
    "children_count": {},
    "zip_codes": [],
    "geo": {
      "lat": "18.309",
      "lon": "101.966"
    },
    "metadata": {},
    "source": {}
  },
  {
    "id": "1661665",
    "level": 3,
    "level_name": {
      "local": "ບ້ານ",
      "en": "Village"
    },
    "name": {
      "local": "Ban Nalè",
      "en": "Ban Nale",
      "slug": "ban-nale-1661665"
    },
    "code": {
      "id": "1661665",
      "iso": null
    },
    "parent": {
      "id": "VI-06",
      "level": 2,
      "name": {
        "local": "Meun",
        "en": "Meun",
        "slug": "meun-vi-06"
      }
    },
    "ancestors": [
      {
        "id": "VI",
        "level": 1,
        "name": {
          "local": "Vientiane",
          "en": "Vientiane Province",
          "slug": "vientiane-province-vi"
        }
      },
      {
        "id": "VI-06",
        "level": 2,
        "name": {
          "local": "Meun",
          "en": "Meun",
          "slug": "meun-vi-06"
        }
      }
    ],
    "children_count": {},
    "zip_codes": [],
    "geo": {
      "lat": "18.364",
      "lon": "101.967"
    },
    "metadata": {},
    "source": {}
  },
  {
    "id": "1661667",
    "level": 3,
    "level_name": {
      "local": "ບ້ານ",
      "en": "Village"
    },
    "name": {
      "local": "Ban Nalèng-Nua",
      "en": "Ban Naleng-Nua",
      "slug": "ban-naleng-nua-1661667"
    },
    "code": {
      "id": "1661667",
      "iso": null
    },
    "parent": {
      "id": "VI-06",
      "level": 2,
      "name": {
        "local": "Meun",
        "en": "Meun",
        "slug": "meun-vi-06"
      }
    },
    "ancestors": [
      {
        "id": "VI",
        "level": 1,
        "name": {
          "local": "Vientiane",
          "en": "Vientiane Province",
          "slug": "vientiane-province-vi"
        }
      },
      {
        "id": "VI-06",
        "level": 2,
        "name": {
          "local": "Meun",
          "en": "Meun",
          "slug": "meun-vi-06"
        }
      }
    ],
    "children_count": {},
    "zip_codes": [],
    "geo": {
      "lat": "18.214",
      "lon": "101.922"
    },
    "metadata": {},
    "source": {}
  },
  {
    "id": "1941624",
    "level": 3,
    "level_name": {
      "local": "ບ້ານ",
      "en": "Village"
    },
    "name": {
      "local": "Ban Nalèng-Tai",
      "en": "Ban Naleng-Tai",
      "slug": "ban-naleng-tai-1941624"
    },
    "code": {
      "id": "1941624",
      "iso": null
    },
    "parent": {
      "id": "VI-06",
      "level": 2,
      "name": {
        "local": "Meun",
        "en": "Meun",
        "slug": "meun-vi-06"
      }
    },
    "ancestors": [
      {
        "id": "VI",
        "level": 1,
        "name": {
          "local": "Vientiane",
          "en": "Vientiane Province",
          "slug": "vientiane-province-vi"
        }
      },
      {
        "id": "VI-06",
        "level": 2,
        "name": {
          "local": "Meun",
          "en": "Meun",
          "slug": "meun-vi-06"
        }
      }
    ],
    "children_count": {},
    "zip_codes": [],
    "geo": {
      "lat": "18.199",
      "lon": "101.924"
    },
    "metadata": {},
    "source": {}
  },
  {
    "id": "1661578",
    "level": 3,
    "level_name": {
      "local": "ບ້ານ",
      "en": "Village"
    },
    "name": {
      "local": "Ban Namhi",
      "en": "Ban Namhi",
      "slug": "ban-namhi-1661578"
    },
    "code": {
      "id": "1661578",
      "iso": null
    },
    "parent": {
      "id": "VI-06",
      "level": 2,
      "name": {
        "local": "Meun",
        "en": "Meun",
        "slug": "meun-vi-06"
      }
    },
    "ancestors": [
      {
        "id": "VI",
        "level": 1,
        "name": {
          "local": "Vientiane",
          "en": "Vientiane Province",
          "slug": "vientiane-province-vi"
        }
      },
      {
        "id": "VI-06",
        "level": 2,
        "name": {
          "local": "Meun",
          "en": "Meun",
          "slug": "meun-vi-06"
        }
      }
    ],
    "children_count": {},
    "zip_codes": [],
    "geo": {
      "lat": "18.037",
      "lon": "101.891"
    },
    "metadata": {},
    "source": {}
  },
  {
    "id": "1658247",
    "level": 3,
    "level_name": {
      "local": "ບ້ານ",
      "en": "Village"
    },
    "name": {
      "local": "Ban Vang",
      "en": "Ban Vang",
      "slug": "ban-vang-1658247"
    },
    "code": {
      "id": "1658247",
      "iso": null
    },
    "parent": {
      "id": "VI-06",
      "level": 2,
      "name": {
        "local": "Meun",
        "en": "Meun",
        "slug": "meun-vi-06"
      }
    },
    "ancestors": [
      {
        "id": "VI",
        "level": 1,
        "name": {
          "local": "Vientiane",
          "en": "Vientiane Province",
          "slug": "vientiane-province-vi"
        }
      },
      {
        "id": "VI-06",
        "level": 2,
        "name": {
          "local": "Meun",
          "en": "Meun",
          "slug": "meun-vi-06"
        }
      }
    ],
    "children_count": {},
    "zip_codes": [],
    "geo": {
      "lat": "18.053",
      "lon": "101.847"
    },
    "metadata": {},
    "source": {}
  }
]